setup.cfg
setup.py
src/fbconsole.py
src/fbconsole.egg-info/PKG-INFO
src/fbconsole.egg-info/SOURCES.txt
src/fbconsole.egg-info/dependency_links.txt
src/fbconsole.egg-info/entry_points.txt
src/fbconsole.egg-info/requires.txt
src/fbconsole.egg-info/top_level.txt
src/fbconsole.egg-info/zip-safe