Metadata-Version: 1.1
Name: fbconsole
Version: 0.4
Summary: A simple facebook api client for writing command line scripts.
Home-page: http://github.com/fbsamples/fbconsole
Author: Paul Carduner, Facebook
Author-email: pcardune@fb.com
License: Apache 2.0
Platform: UNKNOWN
Classifier: Development Status :: 3 - Alpha
Classifier: Environment :: Console
Classifier: Intended Audience :: Developers
Classifier: License :: OSI Approved :: Apache Software License
Classifier: Operating System :: OS Independent
Classifier: Topic :: Utilities
